img2unicode/Ubuntu Mono.npz
img2unicode/__init__.py
img2unicode/dual.py
img2unicode/gamma.py
img2unicode/renderer.py
img2unicode/templates.py
img2unicode/unicodeit.py
img2unicode/utils.py
img2unicode-0.1a11.data/scripts/imgcat
img2unicode-0.1a11.data/scripts/termview
img2unicode-0.1a11.dist-info/LICENSE
img2unicode-0.1a11.dist-info/METADATA
img2unicode-0.1a11.dist-info/WHEEL
img2unicode-0.1a11.dist-info/top_level.txt
img2unicode-0.1a11.dist-info/RECORD
