Metadata-Version: 2.1
Name: img2unicode
Version: 0.1a11
Summary: Convert images to unicode based on font templates. Especially usable in terminal.
Home-page: https://github.com/matrach/img2unicode
Author: Maciej Matraszek
Author-email: matraszek.maciej@gmail.com
License: MIT
Classifier: Programming Language :: Python :: 3
Classifier: License :: OSI Approved :: MIT License
Classifier: Operating System :: OS Independent
Requires-Python: >=3.7
Provides-Extra: develop
Provides-Extra: n2
Provides-Extra: termview
License-File: LICENSE
